adbkit/README.MD
adbkit/__init__.py
adbkit/requirements.txt
adbkit/thirdparty.json
adbkit-0.25.dist-info/LICENSE.rst
adbkit-0.25.dist-info/METADATA
adbkit-0.25.dist-info/WHEEL
adbkit-0.25.dist-info/top_level.txt
adbkit-0.25.dist-info/RECORD
