Metadata-Version: 2.1
Name: adbkit
Version: 0.25
Summary: Big automation package for ADB
Home-page: https://github.com/hansalemaos/adbkit
Author: Johannes Fischer
Author-email: aulasparticularesdealemaosp@gmail.com
License: MIT
Keywords: adb,android,automation,shell,root
Classifier: Development Status :: 4 - Beta
Classifier: Programming Language :: Python :: 3 :: Only
Classifier: Programming Language :: Python :: 3.10
Classifier: Topic :: Software Development :: Libraries :: Python Modules
Classifier: Topic :: Utilities
License-File: LICENSE.rst
Requires-Dist: Pillow
Requires-Dist: a-cv2-imshow-thread
Requires-Dist: a-cv2-shape-finder
Requires-Dist: a-cv-imwrite-imread-plus
Requires-Dist: a-pandas-ex-adb-execute-activities
Requires-Dist: a-pandas-ex-adb-settings-to-df
Requires-Dist: a-pandas-ex-adb-to-df
Requires-Dist: a-pandas-ex-apply-ignore-exceptions
Requires-Dist: a-pandas-ex-csv-plus
Requires-Dist: a-pandas-ex-image-tools
Requires-Dist: a-pandas-ex-logcat2df
Requires-Dist: a-pandas-ex-tesseract-multirow-regex-fuzz
Requires-Dist: adb-grep-search
Requires-Dist: adb-push-create
Requires-Dist: adb-unicode-keyboard
Requires-Dist: adbblitz
Requires-Dist: adbdevicechanger
Requires-Dist: adbescapes
Requires-Dist: androdf
Requires-Dist: bstconnect
Requires-Dist: check-if-nan
Requires-Dist: cv2imshow
Requires-Dist: flatten-everything
Requires-Dist: getevent-sendevent
Requires-Dist: kthread
Requires-Dist: numpy
Requires-Dist: opencv-python
Requires-Dist: pandas
Requires-Dist: psutil
Requires-Dist: pyperclip
Requires-Dist: rapidfuzz
Requires-Dist: regex
Requires-Dist: sendevent-getevent-keyboard
Requires-Dist: sendevent-touch
Requires-Dist: subprocess-print-and-capture
Requires-Dist: taskkill
Requires-Dist: tesseractmultiprocessing
Requires-Dist: touchtouch
